Metadata-Version: 2.1
Name: pyedgeloop
Version: 0.0.2
Summary: An efficient and fast library to detect loops, edges and outer boundary in binary images
Home-page: UNKNOWN
Author: Aditya Dutt
Author-email: adityadutt1996@gmail.com
License: UNKNOWN
Platform: UNKNOWN
Classifier: Programming Language :: Python :: 3
Classifier: License :: OSI Approved :: MIT License
Classifier: Operating System :: OS Independent
Requires-Python: >=3.6
